quantum_trade_utilities/__init__.py
quantum_trade_utilities/analysis/__init__.py
quantum_trade_utilities/analysis/backtest_summary.py
quantum_trade_utilities/analysis/exch_list.py
quantum_trade_utilities/core/__init__.py
quantum_trade_utilities/core/detect_os.py
quantum_trade_utilities/core/exceptions.py
quantum_trade_utilities/core/get_path.py
quantum_trade_utilities/core/propcase.py
quantum_trade_utilities/data/__init__.py
quantum_trade_utilities/data/load_credentials.py
quantum_trade_utilities/data/mongo_coll_verification.py
quantum_trade_utilities/data/mongo_conn.py
quantum_trade_utilities/data/request_url_constructor.py
quantum_trade_utilities/debug/__init__.py
quantum_trade_utilities/debug/debug_util.py
quantum_trade_utilities/io/__init__.py
quantum_trade_utilities/io/delete_logs.py
quantum_trade_utilities/io/grab_html.py
quantum_trade_utilities/io/logging_config.py
quantum_trade_utilities/time/__init__.py
quantum_trade_utilities/time/is_trading_time.py
quantum_trade_utilities/time/std_article_time.py
quantum_trade_utilities/viz/darkviz.py
quantum_trade_utilities-0.1.24.dist-info/METADATA
quantum_trade_utilities-0.1.24.dist-info/WHEEL
quantum_trade_utilities-0.1.24.dist-info/RECORD
