Metadata-Version: 2.4
Name: quantum-trade-utilities
Version: 0.1.24
Summary: Shared utilities for Quantum Trade
Project-URL: Homepage, https://github.com/japoeder/quantum-trade-utilities
Project-URL: Bug Tracker, https://github.com/japoeder/quantum-trade-utilities/issues
Author-email: Jonathan Poeder <jaoeder@gmail.com>
Classifier: License :: OSI Approved :: MIT License
Classifier: Operating System :: OS Independent
Classifier: Programming Language :: Python :: 3
Requires-Python: >=3.10
Requires-Dist: beautifulsoup4
Requires-Dist: debugpy
Requires-Dist: pymongo
Requires-Dist: python-dotenv
Requires-Dist: requests
Requires-Dist: selenium
Provides-Extra: dev
Requires-Dist: pre-commit; extra == 'dev'
Requires-Dist: pylint; extra == 'dev'
Requires-Dist: pytest; extra == 'dev'
Provides-Extra: test
Requires-Dist: coverage; extra == 'test'
Requires-Dist: pytest; extra == 'test'
Requires-Dist: pytest-cov; extra == 'test'
